MANIFEST.in
README.rst
flatbencode.py
setup.py
flatbencode.egg-info/PKG-INFO
flatbencode.egg-info/SOURCES.txt
flatbencode.egg-info/dependency_links.txt
flatbencode.egg-info/top_level.txt