Metadata-Version: 1.1
Name: flatbencode
Version: 0.2.0
Summary: Fast, safe and non-recursive implementation of Bittorrent bencoding for Python 3
Home-page: http://github.com/acatton/flatbencode
Author: Antoine Catton
Author-email: UNKNOWN
License: MIT
Keywords: bencoding bencode bittorrent fast non-recursive stack maximum recursion
Platform: UNKNOWN
Classifier: Development Status :: 4 - Beta
Classifier: Intended Audience :: Developers
Classifier: License :: OSI Approved :: MIT License
Classifier: Programming Language :: Python :: 3.4
Classifier: Programming Language :: Python :: 3.5
Classifier: Programming Language :: Python :: 3.6
Classifier: Programming Language :: Python :: 3 :: Only
Classifier: Topic :: Communications :: File Sharing
Classifier: Topic :: Software Development :: Libraries :: Python Modules
